{
  "root": "أ ج ر",
  "entries": [
    {
      "source_book": "ibn_faris",
      "definition": "كتاب الهمزة\n\nأثم\n\n(أجر) الهمزة والجيم والراء أصلان يمكن الجمعُ بينهما بالمعنى، فالأول الكِراء على العمل، والثاني جَبْر العظم الكَسِير. فأمّا الكِراء فالأجر والأُجْرة. وكان الخليل يقول: الأجْر جزاء العمل، والفعل أجَرَ يَأجُرُ أَجْرا، والمفعول",
      "definition_english": null
    },
    {
      "source_book": "quranic_usage",
      "definition": "ʾ–j–r wages, reward for work done; to hire, to engage; rent, to\nrent; dowry. Of this root, four forms occur 108 times in the\nQur’an: تَأْجُر taʾjur once; اِسْتَأْجَر istaʾjara twice; أَجْر ʾajr 93 times\nand أُجُور ʾujūr 12 times.\n\nتَأْجُر taʾjur [imperf. of v. أَجَرَ ʾajara, trans.] to go into\ncontractual agreement, to work as a hired person or to hire\nsomeone to work as a hired person (28:27) إِنِّي أُرِيدُ أَنْ أُنكِحَكَ إِحْدَى ابْنَتَيَّ\nهَاتَيْنِ عَلَى أَنْ تَأْجُرَنِي ثَمَانِيَ حِجَجٍ I wish to marry you to one of these two\ndaughters of mine, on condition that you hire yourself to me for\neight years.\n\nاِسْتَأْجَر istaʾjara [v. X trans.] to hire, to rent (28:26) قَالَتْ إِحْدَاهُمَا\nيَاأَبَتِ اسْتَأْجِرْهُ إِنَّ خَيْرَ مَنِ اسْتَأْجَرْتَ الْقَوِيُّ الأَمِينُ one of the two [daughters]\nsaid, ‘Father, hire him–the strong, trustworthy man is the best\nperson you could hire.’\n\nأَجْر ʾajr [n., pl. أُجُور ʾujūr] 1 wages, payment for work done\n(65:6) فَإِنْ أَرْضَعْنَ لَكُمْ فَآتُوهُنَّ أُجُورَهُنَّ if they suckle [your babies] for\nyou, pay them their wages [for it] 2 reward (26:109) وَمَا أَسْأَلُكُمْ عَلَيْهِ\nمِنْ أَجْرٍ إِنْ أَجْرِيَ إِلاَّ عَلَى رَبِّ الْعَالَمِينَ I do not ask you any reward for it,\nfor my only reward is with the Lord of all beings 3 dowry (4:25)\nفَانكِحُوهُنَّ بِإِذْنِ أَهْلِهِنَّ وَآتُوهُنَّ أُجُورَهُنَّ بِالْمَعْرُوفِ so marry them with their\npeople’s consent and give them their dowries in accordance with\nthe norms.",
      "definition_english": "ʾ–j–r wages, reward for work done; to hire, to engage; rent, to\nrent; dowry. Of this root, four forms occur 108 times in the\nQur’an: تَأْجُر taʾjur once; اِسْتَأْجَر istaʾjara twice; أَجْر ʾajr 93 times\nand أُجُور ʾujūr 12 times.\n\nتَأْجُر taʾjur [imperf. of v. أَجَرَ ʾajara, trans.] to go into\ncontractual agreement, to work as a hired person or to hire\nsomeone to work as a hired person (28:27) إِنِّي أُرِيدُ أَنْ أُنكِحَكَ إِحْدَى ابْنَتَيَّ\nهَاتَيْنِ عَلَى أَنْ تَأْجُرَنِي ثَمَانِيَ حِجَجٍ I wish to marry you to one of these two\ndaughters of mine, on condition that you hire yourself to me for\neight years.\n\nاِسْتَأْجَر istaʾjara [v. X trans.] to hire, to rent (28:26) قَالَتْ إِحْدَاهُمَا\nيَاأَبَتِ اسْتَأْجِرْهُ إِنَّ خَيْرَ مَنِ اسْتَأْجَرْتَ الْقَوِيُّ الأَمِينُ one of the two [daughters]\nsaid, ‘Father, hire him–the strong, trustworthy man is the best\nperson you could hire.’\n\nأَجْر ʾajr [n., pl. أُجُور ʾujūr] 1 wages, payment for work done\n(65:6) فَإِنْ أَرْضَعْنَ لَكُمْ فَآتُوهُنَّ أُجُورَهُنَّ if they suckle [your babies] for\nyou, pay them their wages [for it] 2 reward (26:109) وَمَا أَسْأَلُكُمْ عَلَيْهِ\nمِنْ أَجْرٍ إِنْ أَجْرِيَ إِلاَّ عَلَى رَبِّ الْعَالَمِينَ I do not ask you any reward for it,\nfor my only reward is with the Lord of all beings 3 dowry (4:25)\nفَانكِحُوهُنَّ بِإِذْنِ أَهْلِهِنَّ وَآتُوهُنَّ أُجُورَهُنَّ بِالْمَعْرُوفِ so marry them with their\npeople’s consent and give them their dowries in accordance with\nthe norms."
    }
  ],
  "occurrences": [
    "10:72:6",
    "10:72:8",
    "11:115:6",
    "11:11:9",
    "11:29:7",
    "11:51:5",
    "11:51:7",
    "12:104:5",
    "12:56:16",
    "12:57:1",
    "12:90:22",
    "16:41:13",
    "16:96:11",
    "16:97:14",
    "17:9:15",
    "18:2:14",
    "18:30:9",
    "18:77:24",
    "25:57:6",
    "26:109:5",
    "26:109:7",
    "26:127:5",
    "26:127:7",
    "26:145:5",
    "26:145:7",
    "26:164:5",
    "26:164:7",
    "26:180:5",
    "26:180:7",
    "26:41:8",
    "28:25:11",
    "28:26:4",
    "28:26:8",
    "28:27:11",
    "28:54:3",
    "29:27:11",
    "29:58:16",
    "2:112:9",
    "2:262:16",
    "2:274:9",
    "2:277:11",
    "2:62:16",
    "33:29:13",
    "33:31:9",
    "33:35:29",
    "33:44:7",
    "33:50:9",
    "34:47:5",
    "34:47:9",
    "35:30:2",
    "35:7:12",
    "36:11:11",
    "36:21:5",
    "38:86:6",
    "39:10:19",
    "39:35:8",
    "39:74:15",
    "3:136:14",
    "3:171:10",
    "3:172:14",
    "3:179:35",
    "3:185:7",
    "3:199:24",
    "3:57:7",
    "41:8:7",
    "42:23:14",
    "42:40:8",
    "47:36:10",
    "48:10:24",
    "48:16:18",
    "48:29:53",
    "49:3:16",
    "4:100:25",
    "4:114:25",
    "4:146:17",
    "4:152:13",
    "4:162:25",
    "4:173:7",
    "4:24:27",
    "4:25:27",
    "4:40:14",
    "4:67:5",
    "4:74:20",
    "4:95:32",
    "52:40:3",
    "57:11:11",
    "57:18:11",
    "57:19:12",
    "57:27:36",
    "57:7:14",
    "5:5:26",
    "5:9:9",
    "60:10:37",
    "64:15:7",
    "65:5:14",
    "65:6:24",
    "67:12:8",
    "68:3:3",
    "68:46:3",
    "6:90:11",
    "73:20:72",
    "7:113:7",
    "7:170:9",
    "84:25:7",
    "8:28:9",
    "95:6:7",
    "9:120:51",
    "9:22:7"
  ]
}