{
  "root": "أ ر ط",
  "entries": [
    {
      "source_book": "ibn_faris",
      "definition": "كتاب الهمزة\n\nأرط\n\nوالإراض: بِساطٌ ضخم من وبَرٍ أو صُوف. ويقال فلانٌ ابنُ أرضٍ، أي غريب. قال:\n\n* أتانا ابْنُ أَرْضٍ يَبْتغي الزَّاد بعدما *\n\nويقال: تأرّض فلانٌ إذا لزِم الأرضَ. قال رجلٌ من بني سعد:\n\nوصاحبٍ نبّهتُه ليَنْهضَا\n\nفقام ما التاثَ ولا تَأَرَّضَا\n\n(أرط) الهمزة والراء والطاء كلمة واحدة لا اشتقاق لها، وهي الأَرْطَى الشجرة، الواحدة منها أرْطاة، وأرْطاتان وأرْطَيَاتٌ. وأَرْطَىً منوَّن، قال أبو عمرو: أرْطاةٌ وأرْطىً، لم تُلحَق الألف للتأنيث. قال العجّاج:\n\n* في مَعْدِنِ الضَّالِ وأرطىً مُعْبِلِ *\n\nوهو يُجرَى ولا يُجْرَى.ويقال هذا أرْطىً كثير وهذه أرْطَى كثيرة. ويقال أَرْطَتِ الأرض: أنبتت الأَرْطى، فهي مُرْطِئةٌ . وذكر الخليل كلمةً إنْ صحّت فهي من الإبدال، أُقيمت الهمزةُ فيها مُقام الهاء. قال الخليل: الأرِيط: العاقِرُ من الرِّجال. وأنشد:",
      "definition_english": null
    }
  ],
  "occurrences": []
}