{
  "root": "ب ع ق",
  "entries": [
    {
      "source_book": "ibn_faris",
      "definition": "كتاب الباء\n\nبعق\n\n(باب الباء والعين وما يثلثهما)\n\n(بعق) الباء والعين والقاف أصلٌ واحد، وهو شقُّ الشّيء وفَتْحُه. ثمّ يُتَّسَع فيه فيُحمَل عليه ما يقاربُه. قال الخليل: البُعَاقُ شدّة الصوت. والمطر البُعاق، بَعَق الوابلُ إذا انفتح فَجْأَةً. قال أبو زياد: البُعاق من الأمطار أشَدُّها، وقال أرضٌ مبعوقةٌ. قال: والانبعاقُ أن ينبَعِقَ عليك الشّيءُ فجأةً. وأنشد:\n\nئِعُ حَتْفٍ لم يَخْشَ منه انبعاقَهْ\n\nبينَمَا المرء آمِنٌ راعَه رَا\n\nويقال: بعَقْتُ الإبلَ، أي نَحَرْتُها. وفي الحديث: \"مَنْ هؤلاء الّذِين يَبْعَقُون لِقاحَنا\" أي ينحرونها . أصله من سَيلان الدّم.\n\nقال أبو عليّ: البَعْق الشَّقُّ الذي يكون في أَلْيَة الحافر . حكى بعضُ الأعراب: بَعَقْتُ فُلاناً عن الأمر بَعْقاً، أي مَزَّقْته وكَشَفْته.ومُنْبَعَق المَفَازةِ مُتَّسَعُها. وقال جَنْدَلُ الطُّهَويّ:\n\nمَسَاحِبٌ مَيَّاسَةُ الذُّيُولِ\n\nللرِّيحِ في مَبْعَقِها المَجْهُولِ\n\nقال الضّبيّ في كَلامٍ: \"كانت قِبَلَنَا ذِئْبةٌ مُجْرِيَةٌ، فأقْبَلَتْ هي وعِرْسُها ليلاً، فبَعَقا غَنَمَنا\"، أي شقّقا بطونَها.",
      "definition_english": null
    }
  ],
  "occurrences": []
}