{
  "id": 532,
  "root": "ث و ل",
  "source_book": "ibn_faris",
  "definition": "كتاب الثاء\n\nثور\n\n(ثول) الثاء والواو واللام كلمةٌ واحدةٌ تدلُّ على الاضطراب، وإليها يرجع الفُروع. فالثَّوَلُ داءٌ يصيب الشّاةَ فتسترخي أعضاؤها، وقد يكون في الذُّكْرَانِ أيضاً، يقال تيسٌ أثْوَلُ، وربّما قالوا للأحمق البطيء الخَيْر أثْوَل؛ وهو من الاضطراب. والثَّول الجماعة من النَّحل من هذا، لأنّه إذا تجمَّع اضطراب فتردّدَ بعضُه على بعضٍ. ويقال تَثَوَّلَ القومُ على فُلان تَثوُّلاً، إذا تجمّعُوا عليه.",
  "definition_english": null,
  "occurrences": []
}