{
  "root": "ح ش م",
  "entries": [
    {
      "source_book": "ibn_faris",
      "definition": "كتاب الحاء\n\nحشك - حشم\n\n(حشم) الحاء والشين والميم أصلٌ مشترك، وهو الغَضَب أو قريبٌ منه.\n\nقال أهل اللغة. الحِشْمَة: الانقباضُ والاستحياء. وقال قومٌ: هو الغضب. قال ابن قُتيبة: رُوِي عن بعض فصحاء العرب: إن ذلك مما يُحْشِمُ بني فلانٍ، أي يغضبهم. وذكر آخر أن العرب لا تعرِفُ الحشمةَ إلاَّ الغضب، وأنَّ قولهم لحشَمِ الرجل خدمه، إنما معناه أنّهم الذين يَغْضب لهم ويغْضَبون له.\n\nقال أبو عبيدٍ: قال أبو زيد: حَشَمْتُ الرجل أحْشِمه وأحْشَمْتُه، وهو أن يجلس إليك فتُؤذيَهُ وتُسمعه ما يكره. وابن الأعرابي يقول: حَشَمْتُه فَحَشم، أي أخجلته. وأحشمته: أغضبته. وأنشد:\n\nحشن - حشو/ي\n\nبطيءُ النُّضْجِ مَحشومُ الأكيل\n\nلَعَمْرُكَ إنْ قُرْصَ أبي خُبَيبٍ",
      "definition_english": null
    }
  ],
  "occurrences": []
}