{
  "root": "ح ق ل",
  "entries": [
    {
      "source_book": "ibn_faris",
      "definition": "كتاب الحاء\n\nحفظ - حقل\n\n(حقل) الحاء والقاف واللام أصلٌ واحد، وهو الأرض وما قاربه. فالحَقْل: القَرَاح الطيِّب. ويقال: \"لا يُنبت البَقْلةَ إلا الحَقْلة\". وحَقِيلٌ: موضع. قال:\n\nحقم - حقن - حقو\n\n* مِن ذِي الأبارق إذْ رعَيْنَ حَقِيلا *\n\nوالمُحاقلة التي نُهِي عنها : بيعُ الزّرعِ في سنبُله بحنطةٍ أو شعير.\n\nومن الباب قولهم: حَقِل الفرسُ، في قول بعضهم، إذا أصابَه وجَعٌ في بطْنه من أكل التراب. والأصل الأرض.\n\nويقال حَوْقَل الشَّيْخ، إذا اعتمد بيديه على خَصره إذا مشى؛ وهي الحوقلة. وكأنَّ ذلك مأخوذٌ من قُربِهِ من الأرض. وأمّا قولهم للقارورة حَوقَلَة، فالأصل الحَوْجَلَة. ولعل الجيم أبدِلت قافا.",
      "definition_english": null
    }
  ],
  "occurrences": []
}