{
  "id": 1348,
  "root": "ذ خ ر",
  "source_book": "ibn_faris",
  "definition": "كتاب الذّال\n\nذأب - ذأم\n\n(ذخر) الذال والخاء والراء يدلُّ على إحرازِ شيءٍ يحفظُه. يقال ذخَرْتُ الشّيءَ أَذْخَرُه ذَخْراً. فإذا قلت افتعلت من ذلك قلت ادّخرتُ. ومن الباب المذاخِر، وهو اسمٌ يجمع جَوفَ الإنسان وعُروقَه. قال منظور :\n\nفلمَّا سقيناها العَكِيس تملَّأَتْ\n\nمَذاخِرُها وازداد رَشْحاً وريدُها\n\nويقولون: ملأ البَعيرُ مَذاخِرَه، أي جوفَه. والإذْخِرُ، ليس من الباب: نبتٌ.",
  "definition_english": null,
  "occurrences": [
    "3:49:35"
  ]
}