{
  "id": 1365,
  "root": "ر ت",
  "source_book": "ibn_faris",
  "definition": "كتاب الرّاء\n\nرب\n\nوممكنٌ أن يكون هذا إنّما سُمِّي رِباباً لأنّه إذا أُخِذ فهو يصير كالعَهْد.\n\nومما يشذّ عن هذه الأصول: الرّبْرَب: القطيع من بقر الوحْش. وقد يجوز أن يضمَّ إلى الباب الثالث فيقال إنَّما سُمِّي ربرباً لتجمُّعه، كما قلنا في اشتقاق الرِّبابة.\n\nومن الباب الثالث الرَّبَب، وهو الماء الكثير، سمِّي بذلك لاجتماعه. قال:\n\n* والبُرَّة السَّمْرَاء والماء الرَّبَبْ *\n\nرت - رث - رج\n\nفأمّا رُبَّ فكلمة تستعمَل في الكلام لتقليل الشّيء، تقول: رُبَّ رجلٍ جاءني. ولا يُعْرف لها اشتقاق.\n\n(رت) الراء والتاء ليس أصلاً، لكنَّهم يقولون: الرُّتَّة: العَجَلة في الكلام. ويقال هي الحُكْلَة فيه. ويقولون: الرُّتُوت: الخنازير. وقال ابنُ الأعرابيّ: الرَّتُّ: الرئيس؛ والجمع رُتوتٌ. وكل هذا فممَّا ينبغي أن يُنظَر فيه.",
  "definition_english": null,
  "occurrences": []
}