{
  "id": 1802,
  "root": "س ل ط",
  "source_book": "ibn_faris",
  "definition": "كتاب السّين\n\nسلب\n\n(سلط) السين واللام والطاء أصلٌ واحدٌ، وهو القوّة والقهر. من ذلك السَّلاطة، من التسلط وهو القَهْر، ولذلك سمِّي السُّلْطان سلطاناً. والسلطان: الحُجَّة. والسَّليط من الرجال: الفصيح اللسان الذَّرِب. والسَّليطة: المرأة الصَّخَّابة.\n\nومما شذَّ عن الباب السَّلِيط: الزّيت بلغة أهل اليَمَن، وبلغة غيرهم دهن السِّمسِم.",
  "definition_english": null,
  "occurrences": [
    "10:68:18",
    "11:96:5",
    "12:40:15",
    "14:10:32",
    "14:11:22",
    "14:22:18",
    "15:42:6",
    "16:100:2",
    "16:99:4",
    "17:33:15",
    "17:65:6",
    "17:80:13",
    "18:15:10",
    "22:71:9",
    "23:45:7",
    "27:21:8",
    "28:35:7",
    "30:35:4",
    "34:21:6",
    "37:156:3",
    "37:30:6",
    "3:151:14",
    "40:23:5",
    "40:35:7",
    "40:56:8",
    "44:19:8",
    "4:144:16",
    "4:153:36",
    "4:90:21",
    "4:91:31",
    "51:38:7",
    "52:38:8",
    "53:23:13",
    "55:33:16",
    "59:6:16",
    "69:29:3",
    "6:81:15",
    "7:33:22",
    "7:71:20"
  ]
}