{
  "id": 2118,
  "root": "ش ر ق",
  "source_book": "ibn_faris",
  "definition": "كتاب الشين\n\nشرق\n\nالسَّهْم الشارف من هذا، وهو الذي طال [عهدُهُ] بالصِّيان فانتكث عَقَبُهُ وريشُهُ. قال أوس:\n\nظُهَارٍ لُؤامٍ فهو أعجفُ شارفُ\n\nيُقلِّبُ سَهماً راشَهُ بمناكِبٍ\n\nويزعمون أن شُرَيْفَاً أطولُ جَبَلٍ في الأرض.\n\n(شرق) الشين والراء والقاف أصلٌ واحدٌ يدلُّ على إضاءةٍ وفتحٍ. من ذلك شَرَقَت الشّمسُ، إذا طلعت. وأشرقت، إذا أضاءت. والشُّرُوق: طُلوعها. ويقولون: لا أفعل ذلك ما ذرَّ شارقٌ، أي طَلَعَ، يُرَاد بذلك طُلُوع الشمس. وأيّام التَّشْريق سمِّيت بذلك لأنَّ لحوم الأضاحِي تُشرَّق فيها للشَّمس. وناسٌ يقولون: سمِّيت بذلك لقولهم: \"أشرِقْ ثَبِير، لكيما نُغير\". والمَشْرِقَانِ: مَشْرِقَا الصَّيفِ والشِّتاء. والشَّرْق: المَشْرِق. وقال قوم: إنَّ اللحمَ الأحمرَ يُسمَّى شَرْقاً. فإنْ كان صحيحاً فلأنَّه من حُمرته كأنه مُشْرِق.\n\nومن قياس هذا الباب: الشّاةُ الشّرقاء: المشقوقة الأُذُن، وهو من الفَتح الذي وصفناه.\n\nومما شذَّ عن هذا الباب قولهم: شَرِقَ بالماء، إِذا غَصَّ به شَرَقَاً. قال عديّ:\n\nكنتُ كالغَصَّانِ بالماء اعتصارِي\n\nلو بِغَيْرِ الماءِ حَلْقِي شَرِقٌ",
  "definition_english": null,
  "occurrences": [
    "15:73:3",
    "19:16:10",
    "24:35:23",
    "26:28:3",
    "26:60:2",
    "2:115:2",
    "2:142:14",
    "2:177:7",
    "2:258:31",
    "37:5:7",
    "38:18:7",
    "39:69:1",
    "43:38:9",
    "55:17:2",
    "70:40:4",
    "73:9:2",
    "7:137:6"
  ]
}