{
  "root": "ش ر ف",
  "entries": [
    {
      "source_book": "ibn_faris",
      "definition": "كتاب الشين\n\nشرف\n\nفقيل شرَعَ البعيرُ عنقَه. وقد مَدَّ شِراعَه إذا رفَعَ عُنقَه. وقيل في التَّفسير في قولـه تعالى: ] إِذْ تَأْتِيهِمْ حِيتَانُهُمْ يَوْمَ سَبْتِهِمْ شُرَّعاً [ [الأعراف 163]: إِنّها الرافعةُ رؤوسَها، ومنه قولهم: رُمْحٌ شُرَاعيٌّ، أي طويل، في قول الهُذَليّ . ومن الفتح الذي ذكرناه أوّلاً روايةُ ابنِ السِّكّيت: شرعت الإهاب، إِذا شقَقتَ ما بين رِجلَيه.\n\n(شرف) الشين والراء والفاء أصلٌ يدلُّ على علوٍّ وارتفاع. فالشَّرَف: *العُلُّوّ. والشريف : الرجل العالي. ورجلٌ شريفٌ من قوم أشراف، يقال إِنَّه جمعٌ نادر، كحبيب وأحباب، ويتيم وأيتام. ويقال للذي غَلَبَهُ غيرُه بالشَّرَف مشروف. ويقال استشرفتُ الشّيءَ، إِذا رفعتَ بصرك تنظرُ إليه. ويقال للأنوف الأشراف، الواحدُ شرف. والمَشْرَف : المكان تُشرِف عليه وتعلوه. ومشارف الأرض: أعاليها. والمشرفيّة: منسوبة إلى مَشَارف الشام. ويقال إنَّ الشُّرْفَة: خِيار المال، واشتقاقه من الشُّرْفة التي تُشَرَّفُ بها القصور، والجمع شُرَف. والمُستشرِف من الخيل: العظيم الطَّويل. قال الخليل: سهمٌ شارف: دقيق طويل، وأُذُنٌ شَرْفاءُ: طويلةُ القُوف . ومَنْكِبٌ أشرفُ:عالٍ. فأَمَّا النّاقة الشَّارفُ فهي المُسِنَّة الهَرِمَة من الإِبل، وهذا ممكنٌ أن يكون من العلوّ في السّنّ. وذُكِر عن الخليل أنَّ",
      "definition_english": null
    }
  ],
  "occurrences": []
}