{
  "id": 2016,
  "root": "ش م ل",
  "source_book": "ibn_faris",
  "definition": "كتاب الشين\n\nشمق - شمل\n\n(شمل) الشين والميم واللام أصلان منقاسان مطّردان، كل واحدٍ منهما في معناه وبابه.\n\nفالأوّل يدلُّ على دَوَران الشيء بالشيء وأخْذِهِ إيّاه من جوانبه. من ذلك قولهم: شَمَِلَهم الأمرُ ، إذا عمَّهم. وهذا أمرٌ شاملٌ. ومنه الشَّملَة، وهي كساءٌ يُؤتَزَرُ به ويُشْتَمَل. وجمع الله شَمْله، إِذا دَعَا له بتألُّف أموره، وإِذا تألَّفَتْ اشتمل كلُّ واحدٍ منهما بالآخر .\n\nومن الباب: شملت الشاة، إِذا جعلتَ لها شِمالاً، وهو وعاء كالكيس يدُخَل فيه ضرعُها فيشتمل عليه. وكذلك شَمَلْتُ النَّخلَة، إِذا كانت تنفضُ حَمْلَها فشُدَّت أعذاقُها بقِطَع الأكسية.\n\nومن الباب: المِشْمل: سيفٌ صغير يَشْتَمِل الرَّجُل عليه بثوبه.",
  "definition_english": null,
  "occurrences": [
    "16:48:13",
    "18:17:14",
    "18:18:9",
    "34:15:10",
    "50:17:7",
    "56:41:2",
    "56:41:5",
    "69:25:5",
    "6:143:15",
    "6:144:13",
    "70:37:4",
    "7:17:11"
  ]
}