{
  "id": 2210,
  "root": "ص و ب",
  "source_book": "ibn_faris",
  "definition": "كتاب الصَّاد\n\nصوي - صوب\n\n(صوب) الصاد والواو والباء أصلٌ صحيحٌ يدلُّ على نزولِ شيءٍ واستقرارِهِ قَرَارَه. من ذلك الصَّوَابُ في القول والفعل، كأنَّه أمرٌ نازلٌ مستقِرٌّ قرارَه. وهو خلاف الخطأ. ومنه الصَّوْب، وهو نزول المطر. والنازل صَوبٌ أيضاً. والدّليلُ على صحّة هذا القياس تسميتُهم للصَّواب صَوْباً. قال الشاعر :",
  "definition_english": null,
  "occurrences": [
    "10:107:16",
    "11:81:21",
    "11:81:23",
    "11:89:6",
    "11:89:9",
    "12:56:10",
    "13:13:9",
    "13:31:34",
    "16:34:1",
    "22:11:14",
    "22:11:9",
    "22:35:10",
    "24:43:26",
    "24:63:22",
    "24:63:25",
    "28:47:3",
    "28:47:4",
    "2:156:3",
    "2:156:4",
    "2:19:2",
    "2:264:24",
    "2:265:14",
    "2:265:21",
    "2:266:19",
    "2:266:24",
    "30:36:8",
    "30:48:20",
    "31:17:12",
    "38:36:8",
    "39:51:1",
    "39:51:9",
    "3:117:12",
    "3:120:6",
    "3:146:11",
    "3:153:21",
    "3:165:2",
    "3:165:3",
    "3:165:5",
    "3:166:2",
    "3:172:8",
    "40:28:28",
    "42:30:2",
    "42:30:4",
    "42:39:3",
    "42:48:20",
    "48:25:22",
    "49:6:10",
    "4:62:3",
    "4:62:4",
    "4:72:6",
    "4:72:7",
    "4:73:2",
    "4:78:11",
    "4:78:19",
    "4:79:2",
    "4:79:8",
    "57:22:2",
    "57:22:4",
    "5:106:25",
    "5:106:26",
    "5:49:26",
    "5:52:11",
    "64:11:2",
    "64:11:4",
    "6:124:19",
    "78:38:14",
    "7:100:12",
    "7:131:8",
    "7:156:14",
    "8:25:4",
    "9:120:22",
    "9:50:2",
    "9:50:6",
    "9:50:7",
    "9:51:3",
    "9:52:12",
    "9:90:12"
  ]
}