{
  "root": "ص ك ك",
  "entries": [
    {
      "source_book": "quranic_usage",
      "definition": "ṣ–k–k to slap with the hand, violent strike with a ringing\nsound; to shut, to close. Of this root, one form, صَكَّت ṣakkat,\noccurs once in the Qur’an.\n\nصَكَّ ṣakka u [v. trans.] to slap, smack, smite with loud noise\n(51:29) فَأَقْبَلَتِ امْرَأَتُهُ فِى صَرَّةٍ فَصَكَّتْ وَجْهَهَا then his wife entered with a\nloud cry, and struck her [own] face.",
      "definition_english": "ṣ–k–k to slap with the hand, violent strike with a ringing\nsound; to shut, to close. Of this root, one form, صَكَّت ṣakkat,\noccurs once in the Qur’an.\n\nصَكَّ ṣakka u [v. trans.] to slap, smack, smite with loud noise\n(51:29) فَأَقْبَلَتِ امْرَأَتُهُ فِى صَرَّةٍ فَصَكَّتْ وَجْهَهَا then his wife entered with a\nloud cry, and struck her [own] face."
    }
  ],
  "occurrences": [
    "51:29:5"
  ]
}