{
  "id": 2364,
  "root": "ض ر ح",
  "source_book": "ibn_faris",
  "definition": "كتاب الضاد\n\nضرج\n\n(ضرح) الضاد والراء والحاء أصلان: أحدُّهما رمْي الشّيء، والآخَر لونٌ من الألوان.\n\nفالأوَّلُ قولهم: ضرَحت الشَّيءَ، إِذا رَميتَ به. والشيء المُضْطرَح: المرميّ. والفَرس الضَّروح: النَّضوح برجلهِ. وقوسٌ ضَروح: شديدةُ الدَّفْعِ للسَّهمِ. والضَّرِيح: القبرُ يُحْفَرُ من غير لَحْدٍ، كأنَّ الميت قد رُمِيَ فيه.\n\nوأمّا الآخَر فالأبيض من كلِّ شيء، يقال لـه المَضْرَحيّ. والصَّقْر مضرحيٌّ، والسيِّد مضرحيّ.\n\n(باب الضاد والزاء وما يثلثهما)",
  "definition_english": null,
  "occurrences": []
}