{
  "id": 2626,
  "root": "ع ت ل",
  "source_book": "ibn_faris",
  "definition": "كتاب العين\n\nعتل\n\nقال الخليلُ وغيره: عَتَك فلانٌ [بفلانٍ ]، إذا أقْدَمَ عليه ضرباً لا يُنهنِهُه شيء. قال الأصمعيُّ: هو أن يَحمِلَ عليه حملةَ أخْذٍ وبَطْش. قال الخليل: عَتَكَ الرّجُل يَعْتِك عَتْكاً وعُتُوكاً، إذا ذَهَب في الأرض. والقوس العاتكة طالَ عليها العهدُ حتَّى احمرَّت. قال الهذلي :\n\nكوَقْف العاجِ عاتكة [اللِّيَاطِ ]\n\nوصَفراء البُرايةِ عُودِ نَبْعٍ\n\n[وامرأة عاتكة]، إذا كانت متضمِّخة بالخَلَوق. ومنه عَتَكتِ القوس. قال الخليل: يقال لكلِّ كريم عاتك، أي قديم. وأصله من عَتَكت القَوس.\n\n(عتل) العين والتاء واللام أصلٌ صحيح يدلُّ على شِدّةٍ وقوّة في الشَّيء. من ذلك الرّجل العُتُلّ، وهو الشَّديد القويَّ المصحَّح الجِسم؛ واشتقاقُه من العَتَلة التي يُحفَر بها. والعَتَلة أيضاً: الهِراوة الغليظة من الخشَب، والجمع عَتَل. وقال:\n\nفاجتنبَنَّ عُرَّمَ الذُّوّادِ\n\nوأينما كنتَ من البلادِ\n\nوضَربَهم بالعَتَل الشِّدادِ\n\nومن الباب العَتْل، وهو أن تأخذ بتَلبيب الرّجُل فتَعتِله، أي تجرّه إليك بقوّة",
  "definition_english": null,
  "occurrences": [
    "44:47:2",
    "68:13:1"
  ]
}