{
  "id": 2616,
  "root": "ع ب ق",
  "source_book": "ibn_faris",
  "definition": "كتاب العين\n\nعبق\n\nمدنَّساتِ الرِّيَب العَوابِط\n\nبمنْزلٍ عَفٍّ ولم يُخالِطِ\n\nوالعَبِيطة: الشّاة أو النّاقة المعتَبَطة. قال الشّاعر:\n\nمٍ إذا كان من رِقاقٍ وبُزْل\n\nولـه لا يَنِي عَبائِطُ من كُو\n\nالرِّقاق: الصِّغار من الإبل.\n\n(عبق) العين والباء والقاف أصل صحيح واحد، وهو لزوم الشيء للشيء. من ذلك عَبِق الطيب به، إذا لَصِق ولازَمَ. قال:\n\nفهي صفراءُ كعُرجون العُمُرْ\n\nعَبِقَ العنبرُ والمِسْكُ بها",
  "definition_english": null,
  "occurrences": []
}