{
  "root": "ع ي م",
  "entries": [
    {
      "source_book": "ibn_faris",
      "definition": "كتاب العين\n\nعيق\n\n(عيم) العين والياء والميم كلمةٌ واحدة صحيحة، وهي شهوةُ اللَّبَن: يقال للذي اشْتَهَى اللّبَن عَيْمَانُ، والمرأة عَيْمَى. تقول: عِمْتُ إلى *اللبن عَيْمَة وعَيَماً شديداً قال الخليل: وكلُّ مصدرٍ مثلِ هذا ممّا يكون لِفَعْلان وفَعْلَى، فإذا أنّثت المصدر قلته على فَعْلة خفيفة، وإذا ثقّلتَ فَعَلَى فَعَل ، نحو الحَيَر والحَيْرة. وجمع العَيْمان عَيامَى وَعِيام.",
      "definition_english": null
    }
  ],
  "occurrences": []
}