{
  "id": 2577,
  "root": "ع ن ق",
  "source_book": "ibn_faris",
  "definition": "كتاب العين\n\nعنق\n\n(عنق) العين والنون والقاف أصلٌ واحد صحيح يدلُّ على امتدادٍ في شيء، إمَّا في ارتفاعٍ وإمَّا في انسياح.\n\nفالأوَّل العنُق، وهو وُصْلة ما بين الرّأس والجسد، مذكّر ومؤنَّث، وجمعه أعناق. ورجلٌ أعنق، أي طويل العنُق. وجبلٌ أعنَقُ: مشرِف. ونجدٌ أعنق، وهضْبةٌ عنقاء. وامرأةٌ عنقاءُ: طويلة العنُق. وهَضْبة مُعنِقة أيضاً. قال:\n\nوُرْقَ الحمام جميمُها لم يؤكَلِ\n\nعيطاء مُعْنِقَةٍ يكون أنيسُها\n\nقال الأصمعيّ: المُعَنِّقات مثل المُعْنِقات. قال عُمَر بن لجأ:\n\n* ومن هَضْب الأَرومِ مُعَنِّقات *\n\nقال أبو عمرو: المُعنِّق: الطويل. وأنشد:\n\n* في تامكٍ مثل النَّقا المُعنِّقِ *\n\nقال أبو عمرو: العنقاء فيما يقال: طائرٌ لم يبق إلاّ اسمُه. وسمِّيت عنقاءَ لبياضٍ كانَ في عُنقها وفي المثَل لما لا يوجَد: \"طارت به العَنْقاء\". فأمَّا قولهم للجماعة عُنُق، فقياسه صحيح، لأنَّه شيءٌ يتّصلُ بعضُه ببعض. قال الله تعالى: ] فَظَلَّتْ أَعْنَاقُهُمْ لَهَا خَاضِعِينَ [ [الشعراء 4]، أي جماعتُهم. ألاَ ترى أنَّه قال:(خَاضِعِينَ)، ولو كانت الأعناق أنفُسها لقال خاضعة أو خاضعات. وإلى هذا ذهبَ أبو زيد. وقال النحويُّون: لمّا كانت الأعناقُ مضافةً إليهم رَدَّ الفعل إليهم دونَها.\n\nقال محمد بن يزيد: لمّا كان خضوعُ أهلها بخضوع أعناقهم أخبرَ عنهم،",
  "definition_english": null,
  "occurrences": [
    "13:5:19",
    "17:13:6",
    "17:29:6",
    "26:4:9",
    "34:33:26",
    "36:8:4",
    "38:33:6",
    "40:71:4",
    "8:12:19"
  ]
}