{
  "root": "ع ل ه",
  "entries": [
    {
      "source_book": "ibn_faris",
      "definition": "كتاب العين\n\nعلن - عله\n\n(عله) العين واللام والهاء أصلٌ صحيح. ويمكن أن يكون من بابِ إبدال الهمزةِ عيناً؛ لأنه يَجري مَجرى الأَلَه [والوَلَه]. وهؤلاء الكلماتُ الثّلاثُ من وادٍ واحد، يشتمل على حَيرة وتلدُّد وتسرُّع ومجيءٍ وذَهاب، لا تخلو من هذه المعاني.\n\nقال الخليل: عَلِه الرّجل يَعْلَهُ عَلَهاً فهو عَلْهانُ، إذا نازعَته نفسهُ إلى شيء، وهو دائم العَلَهان. قال:\n\nعَمايةُ قلبٍ دائم العَلَهانِ\n\nأجَدَّت قَرُونِي وانجلَتْ بعد حِقبةٍ\n\nومن الباب: عَلِهَ، إذا اشتدَّ جُوعه، والجائع عَلْهانُ، والمرأة عَلْهَى، والجمع عِلاَهٌ وعَلاَهَى. يقال عَلِهْتُ إلى الشيء، إذا تاقت نفسُك إليه. ومن الباب قولُ ابنِ أحمر:\n\nهِجانٍ ولا نَبني خِباءً لأيِّمِ\n\nعَلِهْنَ فما نرجو حنيناً لِحُرَّةٍ\n\nكأنه يريد: تحيَّرْن فلا استقرارَ لهن. قالوا: والعَلْهانُ والعالِهُ: الظَّليم .",
      "definition_english": null
    }
  ],
  "occurrences": []
}