{
  "id": 2823,
  "root": "غ ر ث",
  "source_book": "ibn_faris",
  "definition": "كتاب الغين\n\nغرب\n\nويقولون: \"هل من مُغَرِّبةِ خَبَرٍ\"، يريدون خبراً أتَى من بُعد.\n\nوفي كتاب الخليل: \"إذا أمْعَنَت الكلابُ في طلب الصَّيد قيل: غرَّبَت\". وفيه نظر.\n\nوالغارب: أعلى الظَّهر والسَّنام. يقال: أَلْقَى حبلَه على غاربه، إذا خلاَّه. والغُراب معروف. والغُرابانِ: نُقرتانِ عند صَلَوَي العَجُز من الفَرس. والغُرَاب: رأس الفأس. ورِجْل الغُراب: نوعٌ من الصَّرِّ. قال الكميت:\n\n* صُرَّ رِجْلَ الغُرابِ *\n\nغرث - غرد - غزل\n\nوالغِربيب: الأسود، كأنّه مشتقٌّ من لون الغُراب. والمُغْرَب: الأبيض الأشفار من كلِّ شيء. والغَرْبيّ: الفضيخ من البُسْر يُنْبَذ. والغَرْبيُّ: صِبْغٌ أحمر.\n\n(غرث) الغين والراء والثاء أصلٌ صحيح يدلُّ على الجُوع. والغَرث: الجوع. ورجلٌ غَرْثانُ. ويستعيرون هذا فيقولون: جاريةٌ غَرْثَى الوِشاح، لأنَّها دقيقةُ الخَصْرِ لا يُملأ وِشاحُها، وكأنَّ وِشاحَها غَرثان.",
  "definition_english": null,
  "occurrences": []
}