{
  "root": "ق ر ت",
  "entries": [
    {
      "source_book": "ibn_faris",
      "definition": "كتاب القاف\n\nقرت - قرح\n\nيا ربَّةَ البيتِ قُومِي غيرَ صاغرةٍ\n\nوقال الشاعر في القُرْب، وهي الخاصرة:\n\nبكلِّ كميتٍ جَلْدةٍ لم تُوَسَّفِ\n\nوكنتُ إذا ما قُرِّبَ الزّادُ مولعاً\n\nكُميتٍ كأنَّها مزادةُ مُخْلِفِ\n\nمُدَاخَلةِ الأقرابِ غيرِ ضئيلةٍ\n\n(قرت) القاف والراء والتاء أُصَيلٌ يدلُّ على قُبْح في سَحْنة . يقولون: قرِت وجه الرجل: تغيّر من حُزْن. وأصل ذلك من قَرَِت الدَّم، إذا يَبِس بين الجلد واللّحم. وهو دمٌ قارت. وقَرِتَ الجلدُ، إذا ضُرِبَ فاسودَّ.",
      "definition_english": null
    }
  ],
  "occurrences": []
}