{
  "id": 3171,
  "root": "ق ر ع",
  "source_book": "ibn_faris",
  "definition": "كتاب القاف\n\nقرط - قرع\n\n(قرع) القاف والراء والعين معظمُ البابِ ضربُ الشيء. يقال قَرَعْتُ الشيءَ أقرَعُه: ضربتُه. ومُقارَعة الأبطال: قَرعُ بعضِهم بعضاً. والقَريع: الفَحْل، لأنَّه يَقرع الناقة. والإقراع والمُقارَعة: هي المساهمَة. وسمِّيت بذلك لأنَّها شيءٌ كأنَّه يُضرَب. وقارعتُ فلاناً فقرعتُه، أي أصابتني القُرعةُ دونَه. والقارعة: الشَّديدة من شدائد الدهر؛ وسمِّيت بذلك لأنَّها تقرع الناس، أي تضربُهم بشدَّتها. والقارعة: القِيامةُ، لأنَّها تَضرِبُ وتُصيب النَّاسَ بإقراعها. وقوارِعُ القرآن: الآياتُ التي مَن قَرأها لم يُصِبْه فزَع. وكأنها واللهُ أعلمُ- سمِّيت بذلك",
  "definition_english": null,
  "occurrences": [
    "101:1:1",
    "101:2:2",
    "101:3:4",
    "13:31:37",
    "69:4:4"
  ]
}