{
  "id": 3054,
  "root": "ق ل م",
  "source_book": "ibn_faris",
  "definition": "كتاب القاف\n\nقف - قلم\n\n(قلم) القاف واللام والميم أصلٌ صحيح يدلُّ على تسويةِ شيء عند بَرْيه وإصلاحه. من ذلك: قَلَمْتُ الظُّفُر وقلَّمْته. ويقال للضَّعيف: هو مَقلُوم الأظفار. والقُلاَمَة: ما يسقُط من الظُّفُر إذا قُلِم. ومن هذا الباب سمِّي القلمُ\n\nقله قلو\n\nقَلماً، قالوا: سمِّي به لأنَّه يُقْلَم منه كما يُقْلمُ من الظُّفر، ثمَّ شُبِّه القِدْح به فقيل: قلم. ويمكن أن يكون القِدحُ سُمِّي قلماً لما ذكرناه من تسويته وبَرْيه. قال الله تعالى: ] ومَا كُنْتَ لَدَيْهِمْ إِذْ يُلْقُونَ أَقْلاَمَهُمْ [ [آل عمران 44]. ومن الباب المِقْلَم: طَرَف قُنْب البعير، كأنَّه قد قُلِم، ويقال إنّ مَقَالم الرُّمح: كُعوبه.\n\nومما شذَّ عن هذا الأصل القُلاَّم، وهو نبتٌ. قال:\n\nوهل يأكلُ القُلاَّمَ إلا الأباعرُ\n\nأتَوْني بِقُلاَّمٍ فقالوا تَعَشّهُ",
  "definition_english": null,
  "occurrences": [
    "31:27:7",
    "3:44:12",
    "68:1:2",
    "96:4:3"
  ]
}