{
  "root": "ن ص ي",
  "entries": [
    {
      "source_book": "quranic_usage",
      "definition": "ن/ص/ي n–ṣ–y forehead, forelock, hair growing above the forehead,\nto plait hair, to grasp by the forehead; to disgrace someone; to\ncontrol; the upper crust of society, to climb up. Of this root, two\nforms occur four times in the Qur’an: نَاصِيَة nāṣiyatun three times\nand نَوَاصِي nawāṣī once.\n\nنَاصِيَة nāṣiyatun [pl. نَوَاصِي nawāṣī] forelock (55:41) يُعْرَفُ\nالْمُجْرِمُونَ بِسِيمَاهُمْ فَيُؤْخَذُ بِالنَّوَاصِي وَالْأَقْدَامِ the guilty will be known by\ntheir distinguishing marks and will be seized by the forelocks and\nthe feet; *(11:56) آخِذٌ بِنَاصِيَتِهَا being in absolute control over it [lit.\ntaking hold of its forelock].",
      "definition_english": "ن/ص/ي n–ṣ–y forehead, forelock, hair growing above the forehead,\nto plait hair, to grasp by the forehead; to disgrace someone; to\ncontrol; the upper crust of society, to climb up. Of this root, two\nforms occur four times in the Qur’an: نَاصِيَة nāṣiyatun three times\nand نَوَاصِي nawāṣī once.\n\nنَاصِيَة nāṣiyatun [pl. نَوَاصِي nawāṣī] forelock (55:41) يُعْرَفُ\nالْمُجْرِمُونَ بِسِيمَاهُمْ فَيُؤْخَذُ بِالنَّوَاصِي وَالْأَقْدَامِ the guilty will be known by\ntheir distinguishing marks and will be seized by the forelocks and\nthe feet; *(11:56) آخِذٌ بِنَاصِيَتِهَا being in absolute control over it [lit.\ntaking hold of its forelock]."
    }
  ],
  "occurrences": [
    "11:56:13",
    "55:41:5",
    "96:15:6",
    "96:16:1"
  ]
}