{
  "id": 4415,
  "root": "و ش ع",
  "source_book": "ibn_faris",
  "definition": "كتاب الواو\n\nوسل - وسم\n\n(وشع) الواو والشين والعين: أصلٌ واحد يدلُّ على نَسجِ شيءٍ أو تزيينِه أو ما أشبَهَ ذلك. الوشيعة: خشبَةٌ يُلَفُّ بها الغَزْل من ألوانٍ شَتَّى، كلُّ لفيفةٍ منه وَشيعة. ويقال: أوْشَعَتِ الأرضُ: بدا زَهرُها. والوَشيع: حصير يُتَّخذ من ثُمام. والتَّوشيع: رَقْم الثَّوب. والوَشائع: طرائق الغُبار. ووَشَّعَه الشَّيب. ومما ليس من الباب وشَعْتُ الجبَل: صَعِدت.",
  "definition_english": null,
  "occurrences": []
}