{
  "id": 4388,
  "root": "و ر ك",
  "source_book": "ibn_faris",
  "definition": "كتاب الواو\n\nورق\n\nقال أبو عبيد: الوارِقَة: الشَّجرة الخَضْراء الوَرَقِ الحسنةُ. قال: فأمَّا الوَرَاقُ فخُضرةُ الأرضِ من الحَشيش، وليس من الوَرَق. قال:\n\nجرادٌ قد أطاعَ لـه الوَرَاقُ\n\nكأنَّ جيادهنَّ بِرَعْنِ زُمٍّ\n\nووَرَقْتُ الشَّجرَ: أخَذْتُ ورَقَه. وقولهم أوْرَق الصَّائدُ: لم يَصِدْ، هو من الورقِ أيضاً، وذلك لأنَّ الصائد يُلقِي حِبالتَه ويغيب عنها ويأتيها بعد زمان وقد أعْشَبت الأرض وسقط الورقُ على الحِبالة فلا يَهتدِي لها، فلذلك يقال أوْرَقَ، أي صادف الورق قد غَطّى حِبالَتَه. ثمَّ كثُر هذا حتَّى قيل لكلِّ مَن طلب حاجةً ولم يُصِبْها: قد أوْرَقَ. والوَرْقَة، بسكون الراء: أُبْنَةٌ في الغصن خفيّة. فأمَّا الورقة التي هي قطعةٌ من الدم فجمعها وَرَقٌ، هي على معنى التَّشبيه بالوَرَق الذي يتساقط. والوَرَق: الرِّجال الضُّعفاء، شُبِّهوا في ضَعْفهم بوَرَق الشَّجَر.\n\nوالأصل الآخر: الوُرْقة : لونٌ يشبه لونَ الرَّماد. وبعيرٌ أوْرَقُ وحمامةٌ ورقاء، سميت للونها، والرّجلُ كذلك أورق. ويقولون: عامٌ أوْرَق، إذا كان جَدْباً، كأنَّ لونَ الأرضِ لونُ الرَّماد. وسُمِّي عامُ الرَّمادَة لهذا .\n\nورك - ورل - ورم - وره\n\n(ورك) الواو والراء والكاف. كلمةٌ واحدة، هي الوَرِك: ما فوقَ الفَخِذ من مؤخَّر الإنسان. وجلَسَ مُتورِّكاً: ألصق وَرِكَه بالأرض. وتورَّكَ على الدّابّة، في ذلك المعنى. وهذه نعلٌ مَوْرِكَةٌ ، إذا كانت من الوَرِك. والوِرَاكُ: ثوبٌ يُنْسَجُ وَحْدَه يُزَيَّن به ويُحَفُّ به الرَّحْل ، وإنَّما هُو لأنْ يُوضعَ عليه الوَرِك.\n\nوأمَّا الحديثُ أنَّه نَهَى أن يسجُدَ الرّجُل متورِّكاً، فيقال هو أنْ يرفَعَ وَرِكَه في سجوده حَتَّى يُفْحِش. ويقال هو أنْ يُلْصِقَ وركَه بعَقِبَيه في السُّجود والوَرْك في قول الهُذَليّ :\n\nإذا مُطْيَ حَنَّ بِوَرْكٍ حُدَالِ\n\nبها مَحِصٌ غيرُ جافِي القُوَى\n\nفإنَّه وتَرٌ فُتِل من الوَرِك.",
  "definition_english": null,
  "occurrences": []
}